pvinspect/__init__.py
pvinspect/common/__init__.py
pvinspect/common/_ipy_exit.py
pvinspect/common/transform.py
pvinspect/common/util.py
pvinspect/data/__init__.py
pvinspect/data/demo.py
pvinspect/data/exceptions.py
pvinspect/data/image.py
pvinspect/data/io.py
pvinspect/preproc/__init__.py
pvinspect/preproc/detection.py
pvinspect/preproc/_mdetect/__init__.py
pvinspect/preproc/_mdetect/config.py
pvinspect/preproc/_mdetect/locate.py
pvinspect/preproc/_mdetect/locate_corners.py
pvinspect/preproc/_mdetect/locate_module.py
pvinspect/preproc/_mdetect/summary.py
test/__init__.py
test/conftest.py
test/test_detection.py
test/test_image.py
test/test_io.py
test/test_transform.py
test/utilities.py
pvinspect-0.0.1.dist-info/LICENSE
pvinspect-0.0.1.dist-info/METADATA
pvinspect-0.0.1.dist-info/WHEEL
pvinspect-0.0.1.dist-info/top_level.txt
pvinspect-0.0.1.dist-info/RECORD
