Metadata-Version: 2.1
Name: pvinspect
Version: 0.0.1
Summary: Provides methods for the analysis of PV modules using different modailities
Home-page: https://github.com/ma0ho/pvinspect
Author: Mathis Hoffmann
Author-email: mathis.hoffmann@fau.de
License: UNKNOWN
Platform: UNKNOWN
Classifier: Programming Language :: Python :: 3
Classifier: License :: OSI Approved :: Apache Software License
Classifier: Operating System :: OS Independent
Requires-Python: >=3.6, <3.8
Requires-Dist: numpy
Requires-Dist: scikit-image
Requires-Dist: matplotlib
Requires-Dist: ipywidgets
Requires-Dist: pathlib
Requires-Dist: tqdm
Requires-Dist: pytest
Requires-Dist: scipy
Requires-Dist: opencv-python
Requires-Dist: requests
Requires-Dist: googledrivedownloader
Requires-Dist: jupyterlab
